{"0": [{"x": 147, "y": 146, "position": -4, "pitch": "E4", "duration": 7}, {"x": 196, "y": 142, "position": -3, "pitch": "F#4", "duration": 7}, {"x": 245, "y": 138, "position": -2, "pitch": "G4", "duration": 7}, {"x": 294, "y": 134, "position": -1, "pitch": "A4", "duration": 7}, {"x": 343, "y": 132, "position": 0, "pitch": "B4", "duration": 7}, {"x": 392, "y": 155, "position": -4, "pitch": "E4", "duration": 7}, {"x": 456, "y": 163, "position": -5, "pitch": "D#4", "duration": 6}, {"x": 530, "y": 160, "position": -4, "pitch": "E4", "duration": 7}, {"x": 577, "y": 156, "position": -3, "pitch": "F#4", "duration": 7}, {"x": 624, "y": 152, "position": -2, "pitch": "G4", "duration": 7}, {"x": 686, "y": 146, "position": -1, "pitch": "A4", "duration": 5}, {"x": 748, "y": 136, "position": 1, "pitch": "C5", "duration": 7}, {"x": 795, "y": 141, "position": 0, "pitch": "B4", "duration": 7}, {"x": 842, "y": 146, "position": -1, "pitch": "A4", "duration": 7}, {"x": 890, "y": 150, "position": -2, "pitch": "G4", "duration": 7}, {"x": 952, "y": 153, "position": -3, "pitch": "F#4", "duration": 5}, {"x": 1015, "y": 170, "position": -7, "pitch": "B3", "duration": 3}], "1": [{"x": 130, "y": 266, "position": -1, "pitch": "A4", "duration": 7}, {"x": 189, "y": 261, "position": 0, "pitch": "B4", "duration": 7}, {"x": 246, "y": 257, "position": 1, "pitch": "C5", "duration": 3}, {"x": 366, "y": 276, "position": -2, "pitch": "G4", "duration": 7}, {"x": 424, "y": 273, "position": -1, "pitch": "A4", "duration": 7}, {"x": 481, "y": 269, "position": 0, "pitch": "B4", "duration": 3}, {"x": 598, "y": 286, "position": -3, "pitch": "F#4", "duration": 7}, {"x": 654, "y": 281, "position": -2, "pitch": "G4", "duration": 7}, {"x": 710, "y": 276, "position": -1, "pitch": "A4", "duration": 7}, {"x": 766, "y": 305, "position": -7, "pitch": "B3", "duration": 7}, {"x": 823, "y": 295, "position": -5, "pitch": "D#4", "duration": 7}, {"x": 878, "y": 284, "position": -3, "pitch": "F#4", "duration": 7}, {"x": 950, "y": 288, "position": -4, "pitch": "E4", "duration": 4}], "2": [{"x": 150, "y": 465, "position": 3, "pitch": "E5", "duration": 4}, {"x": 239, "y": 470, "position": 2, "pitch": "D5", "duration": 7}, {"x": 276, "y": 465, "position": 3, "pitch": "E5", "duration": 7}, {"x": 313, "y": 480, "position": 0, "pitch": "B4", "duration": 5}, {"x": 360, "y": 471, "position": 2, "pitch": "D5", "duration": 5}, {"x": 423, "y": 473, "position": 2, "pitch": "D5", "duration": 5}, {"x": 461, "y": 483, "position": 0, "pitch": "B4", "duration": 5}, {"x": 500, "y": 494, "position": -2, "pitch": "G4", "duration": 5}, {"x": 538, "y": 490, "position": -1, "pitch": "A4", "duration": 1}, {"x": 662, "y": 494, "position": -2, "pitch": "G4", "duration": 4}, {"x": 748, "y": 503, "position": -4, "pitch": "E4", "duration": 7}, {"x": 783, "y": 509, "position": -5, "pitch": "D4", "duration": 7}, {"x": 820, "y": 492, "position": -2, "pitch": "G4", "duration": 7}, {"x": 855, "y": 487, "position": -1, "pitch": "A4", "duration": 7}, {"x": 890, "y": 481, "position": 0, "pitch": "B4", "duration": 7}, {"x": 926, "y": 471, "position": 2, "pitch": "D5", "duration": 7}, {"x": 977, "y": 480, "position": 0, "pitch": "B4", "duration": 2}], "3": [{"x": 130, "y": 600, "position": 3, "pitch": "E5", "duration": 4}, {"x": 223, "y": 605, "position": 2, "pitch": "D5", "duration": 7}, {"x": 262, "y": 600, "position": 3, "pitch": "E5", "duration": 7}, {"x": 300, "y": 589, "position": 5, "pitch": "G5", "duration": 5}, {"x": 341, "y": 600, "position": 3, "pitch": "E5", "duration": 5}, {"x": 383, "y": 606, "position": 2, "pitch": "D5", "duration": 5}, {"x": 438, "y": 618, "position": 0, "pitch": "B4", "duration": 1}, {"x": 554, "y": 623, "position": -1, "pitch": "A4", "duration": 5}, {"x": 603, "y": 618, "position": 0, "pitch": "B4", "duration": 5}, {"x": 666, "y": 628, "position": -2, "pitch": "G4", "duration": 3}, {"x": 733, "y": 606, "position": 2, "pitch": "D5", "duration": 3}, {"x": 801, "y": 636, "position": -4, "pitch": "E4", "duration": 6}, {"x": 858, "y": 640, "position": -5, "pitch": "D4", "duration": 7}, {"x": 911, "y": 624, "position": -2, "pitch": "G4", "duration": 1}], "4": [{"x": 148, "y": 861, "position": -6, "pitch": "C4", "duration": 5}, {"x": 218, "y": 845, "position": -3, "pitch": "F4", "duration": 5}, {"x": 288, "y": 844, "position": -3, "pitch": "F4", "duration": 5}, {"x": 373, "y": 839, "position": -2, "pitch": "G4", "duration": 7}, {"x": 420, "y": 834, "position": -1, "pitch": "A4", "duration": 7}, {"x": 467, "y": 829, "position": 0, "pitch": "Bb4", "duration": 7}, {"x": 513, "y": 833, "position": -1, "pitch": "A4", "duration": 5}, {"x": 580, "y": 843, "position": -3, "pitch": "F4", "duration": 5}, {"x": 663, "y": 847, "position": -4, "pitch": "E4", "duration": 7}, {"x": 708, "y": 841, "position": -3, "pitch": "F4", "duration": 7}, {"x": 753, "y": 836, "position": -2, "pitch": "G4", "duration": 7}, {"x": 799, "y": 841, "position": -3, "pitch": "F4", "duration": 5}, {"x": 866, "y": 850, "position": -5, "pitch": "D4", "duration": 5}, {"x": 950, "y": 855, "position": -6, "pitch": "C4", "duration": 3}, {"x": 1045, "y": 818, "position": 1, "pitch": "C5", "duration": 5}], "5": [{"x": 131, "y": 966, "position": 0, "pitch": "Bb4", "duration": 7}, {"x": 175, "y": 961, "position": 1, "pitch": "C5", "duration": 7}, {"x": 221, "y": 955, "position": 2, "pitch": "D5", "duration": 7}, {"x": 268, "y": 959, "position": 1, "pitch": "C5", "duration": 5}, {"x": 335, "y": 963, "position": 0, "pitch": "Bb4", "duration": 5}, {"x": 417, "y": 967, "position": -1, "pitch": "A4", "duration": 7}, {"x": 463, "y": 961, "position": 0, "pitch": "Bb4", "duration": 7}, {"x": 507, "y": 956, "position": 1, "pitch": "C5", "duration": 7}, {"x": 552, "y": 960, "position": 0, "pitch": "Bb4", "duration": 5}, {"x": 616, "y": 965, "position": -1, "pitch": "A4", "duration": 5}, {"x": 696, "y": 969, "position": -2, "pitch": "G4", "duration": 5}, {"x": 761, "y": 963, "position": -1, "pitch": "A4", "duration": 7}, {"x": 810, "y": 973, "position": -3, "pitch": "F4", "duration": 7}, {"x": 860, "y": 978, "position": -4, "pitch": "E4", "duration": 7}, {"x": 910, "y": 967, "position": -2, "pitch": "G4", "duration": 7}, {"x": 976, "y": 973, "position": -3, "pitch": "F4", "duration": 4}], "6": [{"x": 151, "y": 1212, "position": -5, "pitch": "D4", "duration": 7}, {"x": 175, "y": 1227, "position": -8, "pitch": "A3", "duration": 7}, {"x": 198, "y": 1211, "position": -5, "pitch": "D4", "duration": 7}, {"x": 222, "y": 1206, "position": -4, "pitch": "E4", "duration": 7}, {"x": 244, "y": 1200, "position": -3, "pitch": "F4", "duration": 7}, {"x": 268, "y": 1190, "position": -1, "pitch": "A4", "duration": 7}, {"x": 292, "y": 1194, "position": -2, "pitch": "G4", "duration": 5}, {"x": 322, "y": 1204, "position": -4, "pitch": "E4", "duration": 6}, {"x": 363, "y": 1213, "position": -6, "pitch": "C#4", "duration": 7}, {"x": 402, "y": 1207, "position": -5, "pitch": "D4", "duration": 7}, {"x": 425, "y": 1222, "position": -8, "pitch": "A3", "duration": 7}, {"x": 448, "y": 1205, "position": -5, "pitch": "D4", "duration": 7}, {"x": 472, "y": 1200, "position": -4, "pitch": "E4", "duration": 7}, {"x": 495, "y": 1194, "position": -3, "pitch": "F4", "duration": 7}, {"x": 523, "y": 1178, "position": 0, "pitch": "Bb4", "duration": 7}, {"x": 546, "y": 1183, "position": -1, "pitch": "A4", "duration": 7}, {"x": 576, "y": 1187, "position": -2, "pitch": "G#4", "duration": 7}, {"x": 599, "y": 1182, "position": -1, "pitch": "A4", "duration": 3}, {"x": 683, "y": 1175, "position": 0, "pitch": "Bb4", "duration": 7}, {"x": 706, "y": 1180, "position": -1, "pitch": "A4", "duration": 7}, {"x": 729, "y": 1175, "position": 0, "pitch": "Bb4", "duration": 7}, {"x": 756, "y": 1185, "position": -2, "pitch": "G4", "duration": 5}, {"x": 808, "y": 1179, "position": -1, "pitch": "A4", "duration": 7}, {"x": 838, "y": 1184, "position": -2, "pitch": "G#4", "duration": 7}, {"x": 860, "y": 1179, "position": -1, "pitch": "A4", "duration": 7}, {"x": 883, "y": 1189, "position": -3, "pitch": "F4", "duration": 5}, {"x": 929, "y": 1195, "position": -4, "pitch": "E4", "duration": 6}, {"x": 965, "y": 1199, "position": -5, "pitch": "D4", "duration": 7}, {"x": 997, "y": 1205, "position": -6, "pitch": "C#4", "duration": 7}, {"x": 1021, "y": 1200, "position": -5, "pitch": "D4", "duration": 7}, {"x": 1044, "y": 1195, "position": -4, "pitch": "E4", "duration": 3}, {"x": 1086, "y": 1215, "position": -8, "pitch": "A3", "duration": 5}], "7": [{"x": 135, "y": 1348, "position": -5, "pitch": "D4", "duration": 7}, {"x": 161, "y": 1363, "position": -8, "pitch": "A3", "duration": 7}, {"x": 186, "y": 1347, "position": -5, "pitch": "D4", "duration": 7}, {"x": 212, "y": 1336, "position": -3, "pitch": "F4", "duration": 7}, {"x": 238, "y": 1326, "position": -1, "pitch": "A4", "duration": 7}, {"x": 264, "y": 1310, "position": 2, "pitch": "D5", "duration": 7}, {"x": 289, "y": 1305, "position": 3, "pitch": "E5", "duration": 5}, {"x": 324, "y": 1314, "position": 1, "pitch": "C#5", "duration": 6}, {"x": 364, "y": 1323, "position": -1, "pitch": "A4", "duration": 7}, {"x": 405, "y": 1296, "position": 4, "pitch": "F5", "duration": 6}, {"x": 446, "y": 1301, "position": 3, "pitch": "E5", "duration": 7}, {"x": 470, "y": 1305, "position": 2, "pitch": "D5", "duration": 7}, {"x": 493, "y": 1300, "position": 3, "pitch": "E5", "duration": 7}, {"x": 516, "y": 1294, "position": 4, "pitch": "F5", "duration": 7}, {"x": 539, "y": 1298, "position": 3, "pitch": "E5", "duration": 4}, {"x": 645, "y": 1311, "position": 0, "pitch": "Bb4", "duration": 7}, {"x": 670, "y": 1316, "position": -1, "pitch": "A4", "duration": 7}, {"x": 696, "y": 1321, "position": -2, "pitch": "G4", "duration": 7}, {"x": 721, "y": 1300, "position": 2, "pitch": "D5", "duration": 5}, {"x": 779, "y": 1315, "position": -1, "pitch": "A4", "duration": 7}, {"x": 805, "y": 1320, "position": -2, "pitch": "G4", "duration": 7}, {"x": 831, "y": 1325, "position": -3, "pitch": "F4", "duration": 7}, {"x": 856, "y": 1299, "position": 2, "pitch": "D5", "duration": 5}, {"x": 904, "y": 1294, "position": 3, "pitch": "E5", "duration": 6}, {"x": 944, "y": 1299, "position": 2, "pitch": "D5", "duration": 7}, {"x": 974, "y": 1304, "position": 1, "pitch": "C#5", "duration": 7}, {"x": 996, "y": 1299, "position": 2, "pitch": "D5", "duration": 7}, {"x": 1019, "y": 1294, "position": 3, "pitch": "E5", "duration": 7}, {"x": 1041, "y": 1300, "position": 2, "pitch": "D5", "duration": 4}], "8": [{"x": 155, "y": 1556, "position": -1, "pitch": "A4", "duration": 5}, {"x": 186, "y": 1555, "position": -1, "pitch": "A4", "duration": 7}, {"x": 210, "y": 1544, "position": 1, "pitch": "C5", "duration": 7}, {"x": 233, "y": 1553, "position": -1, "pitch": "A4", "duration": 5}, {"x": 264, "y": 1557, "position": -2, "pitch": "G4", "duration": 5}, {"x": 294, "y": 1561, "position": -3, "pitch": "F4", "duration": 1}, {"x": 382, "y": 1567, "position": -5, "pitch": "D4", "duration": 5}, {"x": 412, "y": 1556, "position": -3, "pitch": "F4", "duration": 3}, {"x": 453, "y": 1550, "position": -2, "pitch": "G4", "duration": 5}, {"x": 484, "y": 1544, "position": -1, "pitch": "A4", "duration": 1}, {"x": 570, "y": 1531, "position": 1, "pitch": "C5", "duration": 6}, {"x": 605, "y": 1525, "position": 2, "pitch": "D5", "duration": 7}, {"x": 627, "y": 1530, "position": 1, "pitch": "C5", "duration": 5}, {"x": 657, "y": 1539, "position": -1, "pitch": "A4", "duration": 5}, {"x": 687, "y": 1543, "position": -2, "pitch": "G4", "duration": 7}, {"x": 711, "y": 1538, "position": -1, "pitch": "A4", "duration": 7}, {"x": 733, "y": 1542, "position": -2, "pitch": "G4", "duration": 7}, {"x": 756, "y": 1547, "position": -3, "pitch": "F4", "duration": 7}, {"x": 779, "y": 1556, "position": -5, "pitch": "D4", "duration": 3}, {"x": 835, "y": 1556, "position": -5, "pitch": "D4", "duration": 7}, {"x": 858, "y": 1546, "position": -3, "pitch": "F4", "duration": 7}, {"x": 881, "y": 1542, "position": -2, "pitch": "G4", "duration": 7}, {"x": 903, "y": 1537, "position": -1, "pitch": "A4", "duration": 7}, {"x": 926, "y": 1542, "position": -2, "pitch": "G4", "duration": 7}, {"x": 950, "y": 1537, "position": -1, "pitch": "A4", "duration": 7}, {"x": 972, "y": 1547, "position": -3, "pitch": "F4", "duration": 7}, {"x": 996, "y": 1557, "position": -5, "pitch": "D4", "duration": 7}, {"x": 1018, "y": 1548, "position": -3, "pitch": "F4", "duration": 7}, {"x": 1042, "y": 1558, "position": -5, "pitch": "D4", "duration": 7}, {"x": 1065, "y": 1564, "position": -6, "pitch": "C4", "duration": 4}], "9": [{"x": 136, "y": 1684, "position": 1, "pitch": "C5", "duration": 6}, {"x": 173, "y": 1693, "position": -1, "pitch": "A4", "duration": 7}, {"x": 196, "y": 1697, "position": -2, "pitch": "G4", "duration": 3}, {"x": 235, "y": 1710, "position": -5, "pitch": "D4", "duration": 7}, {"x": 257, "y": 1699, "position": -3, "pitch": "F4", "duration": 7}, {"x": 280, "y": 1708, "position": -5, "pitch": "D4", "duration": 7}, {"x": 302, "y": 1697, "position": -3, "pitch": "F4", "duration": 7}, {"x": 323, "y": 1691, "position": -2, "pitch": "G4", "duration": 3}, {"x": 379, "y": 1689, "position": -2, "pitch": "G4", "duration": 7}, {"x": 401, "y": 1688, "position": -2, "pitch": "G4", "duration": 7}, {"x": 422, "y": 1693, "position": -3, "pitch": "F4", "duration": 7}, {"x": 444, "y": 1686, "position": -2, "pitch": "G4", "duration": 7}, {"x": 466, "y": 1680, "position": -1, "pitch": "A4", "duration": 5}, {"x": 494, "y": 1669, "position": 1, "pitch": "C5", "duration": 7}, {"x": 516, "y": 1678, "position": -1, "pitch": "A4", "duration": 7}, {"x": 537, "y": 1683, "position": -2, "pitch": "G4", "duration": 6}, {"x": 571, "y": 1676, "position": -1, "pitch": "A4", "duration": 7}, {"x": 592, "y": 1680, "position": -2, "pitch": "G4", "duration": 3}, {"x": 646, "y": 1673, "position": -1, "pitch": "A4", "duration": 6}, {"x": 679, "y": 1682, "position": -3, "pitch": "F4", "duration": 7}, {"x": 700, "y": 1676, "position": -2, "pitch": "G4", "duration": 3}, {"x": 739, "y": 1680, "position": -3, "pitch": "F4", "duration": 7}, {"x": 760, "y": 1675, "position": -2, "pitch": "G4", "duration": 7}, {"x": 782, "y": 1689, "position": -5, "pitch": "D4", "duration": 7}, {"x": 803, "y": 1679, "position": -3, "pitch": "F4", "duration": 7}, {"x": 824, "y": 1674, "position": -2, "pitch": "G4", "duration": 3}, {"x": 878, "y": 1675, "position": -2, "pitch": "G4", "duration": 7}, {"x": 906, "y": 1675, "position": -2, "pitch": "G4", "duration": 5}, {"x": 934, "y": 1670, "position": -1, "pitch": "A4", "duration": 7}, {"x": 956, "y": 1676, "position": -2, "pitch": "G4", "duration": 5}, {"x": 984, "y": 1682, "position": -3, "pitch": "F4", "duration": 5}, {"x": 1012, "y": 1682, "position": -3, "pitch": "F4", "duration": 6}, {"x": 1046, "y": 1693, "position": -5, "pitch": "D4", "duration": 7}, {"x": 1068, "y": 1699, "position": -6, "pitch": "C4", "duration": 3}]}